generate_code/__init__.py
generate_code/__main__.py
generate_code/database.py
generate_code/templates/controller_template.jinja2
generate_code/templates/dto_query_template.jinja2
generate_code/templates/dto_template.jinja2
generate_code/templates/entity_template.jinja2
generate_code/templates/mapper_template.jinja2
generate_code/templates/service_template.jinja2
generate_code/templates/vo_template.jinja2
generate_code-1.0.21.dist-info/METADATA
generate_code-1.0.21.dist-info/WHEEL
generate_code-1.0.21.dist-info/entry_points.txt
generate_code-1.0.21.dist-info/top_level.txt
generate_code-1.0.21.dist-info/RECORD
