Metadata-Version: 2.1
Name: generate-code
Version: 1.0.21
Summary: 一个简单的 Java 代码生成器
Home-page: https://github.com/luojizhen99/generate-code.git
Author: 骆吉振
Author-email: luojizhen99@gmail.com
License: UNKNOWN
Platform: UNKNOWN
Classifier: Programming Language :: Python :: 3
Classifier: License :: OSI Approved :: MIT License
Classifier: Operating System :: OS Independent
Requires-Python: >=3.6
Requires-Dist: sqlalchemy
Requires-Dist: pymysql
Requires-Dist: jinja2
